odoo10_addon_connector_ecommerce-10.0.1.1.1-py3.8-nspkg.pth
odoo/addons/connector_ecommerce/README.rst
odoo/addons/connector_ecommerce/__init__.py
odoo/addons/connector_ecommerce/__manifest__.py
odoo/addons/connector_ecommerce/components/__init__.py
odoo/addons/connector_ecommerce/components/line_builder.py
odoo/addons/connector_ecommerce/components/sale_order_onchange.py
odoo/addons/connector_ecommerce/data/ecommerce_data.xml
odoo/addons/connector_ecommerce/i18n/connector_ecommerce.pot
odoo/addons/connector_ecommerce/i18n/de.po
odoo/addons/connector_ecommerce/i18n/es.po
odoo/addons/connector_ecommerce/i18n/fr.po
odoo/addons/connector_ecommerce/i18n/nl.po
odoo/addons/connector_ecommerce/models/__init__.py
odoo/addons/connector_ecommerce/models/account.py
odoo/addons/connector_ecommerce/models/account_payment_mode.py
odoo/addons/connector_ecommerce/models/event.py
odoo/addons/connector_ecommerce/models/invoice.py
odoo/addons/connector_ecommerce/models/product.py
odoo/addons/connector_ecommerce/models/sale.py
odoo/addons/connector_ecommerce/models/stock.py
odoo/addons/connector_ecommerce/security/ir.model.access.csv
odoo/addons/connector_ecommerce/security/security.xml
odoo/addons/connector_ecommerce/static/description/icon.png
odoo/addons/connector_ecommerce/tests/__init__.py
odoo/addons/connector_ecommerce/tests/test_invoice_event.py
odoo/addons/connector_ecommerce/tests/test_onchange.py
odoo/addons/connector_ecommerce/tests/test_picking_event.py
odoo/addons/connector_ecommerce/unit/__init__.py
odoo/addons/connector_ecommerce/unit/line_builder.py
odoo/addons/connector_ecommerce/unit/sale_order_onchange.py
odoo/addons/connector_ecommerce/views/invoice_view.xml
odoo/addons/connector_ecommerce/views/payment_mode_view.xml
odoo/addons/connector_ecommerce/views/sale_view.xml
odoo/addons/connector_ecommerce/views/stock_view.xml
odoo/addons/connector_ecommerce/wizard/__init__.py
odoo/addons/connector_ecommerce/wizard/sale_ignore_cancel.py
odoo10_addon_connector_ecommerce-10.0.1.1.1.dist-info/METADATA
odoo10_addon_connector_ecommerce-10.0.1.1.1.dist-info/WHEEL
odoo10_addon_connector_ecommerce-10.0.1.1.1.dist-info/namespace_packages.txt
odoo10_addon_connector_ecommerce-10.0.1.1.1.dist-info/top_level.txt
odoo10_addon_connector_ecommerce-10.0.1.1.1.dist-info/RECORD
