Metadata-Version: 2.1
Name: odoo10-addon-connector-ecommerce
Version: 10.0.1.1.1
Summary: Connector for E-Commerce
Home-page: http://odoo-connector.com
Author: Camptocamp,Akretion,Odoo Community Association (OCA)
Author-email: support@odoo-community.org
License: AGPL-3
Platform: UNKNOWN
Classifier: Programming Language :: Python
Classifier: Framework :: Odoo
Classifier: License :: OSI Approved :: GNU Affero General Public License v3
Requires-Python: ~=2.7
Requires-Dist: odoo10-addon-connector
Requires-Dist: odoo10-addon-connector-base-product
Requires-Dist: odoo10-addon-sale-automatic-workflow-payment-mode
Requires-Dist: odoo10-addon-sale-exception
Requires-Dist: odoo (<10.1dev,>=10.0)
